{
  "version": "3.2.2",
  "flags": {},
  "shapes": [
    {
      "label": "cucumber",
      "score": null,
      "points": [
        [
          595.61767578125,
          90.31539916992188
        ],
        [
          618.0284423828125,
          97.91502380371094
        ],
        [
          628.5816650390625,
          123.75259399414062
        ],
        [
          634.676513671875,
          169.0316925048828
        ],
        [
          630.1273193359375,
          238.0843963623047
        ],
        [
          625.38037109375,
          286.34503173828125
        ],
        [
          623.290283203125,
          332.863037109375
        ],
        [
          624.4720458984375,
          372.00469970703125
        ],
        [
          627.9097900390625,
          419.02642822265625
        ],
        [
          638.10498046875,
          455.2845458984375
        ],
        [
          656.96630859375,
          533.4835205078125
        ],
        [
          665.0765380859375,
          565.0527954101562
        ],
        [
          669.0166015625,
          587.244384765625
        ],
        [
          663.8577880859375,
          610.7239379882812
        ],
        [
          650.444580078125,
          617.0438232421875
        ],
        [
          634.8609619140625,
          617.0792236328125
        ],
        [
          601.4105224609375,
          591.6691284179688
        ],
        [
          585.4736328125,
          550.918212890625
        ],
        [
          574.1077880859375,
          509.9222106933594
        ],
        [
          557.999755859375,
          465.9800720214844
        ],
        [
          546.8209228515625,
          411.3723449707031
        ],
        [
          545.671142578125,
          338.6246643066406
        ],
        [
          544.8843994140625,
          204.2496337890625
        ],
        [
          541.120361328125,
          134.04241943359375
        ],
        [
          543.5794677734375,
          111.5076904296875
        ],
        [
          549.3797607421875,
          99.99529266357422
        ],
        [
          555.5224609375,
          94.8653564453125
        ],
        [
          570.93505859375,
          91.63872528076172
        ]
      ],
      "group_id": null,
      "description": "",
      "difficult": false,
      "shape_type": "polygon",
      "flags": {},
      "attributes": {},
      "kie_linking": []
    }
  ],
  "imagePath": "10_20210105_1908774_aug1.JPG",
  "imageData": null,
  "imageHeight": 720,
  "imageWidth": 1280
}