{
  "version": "3.2.2",
  "flags": {},
  "shapes": [
    {
      "label": "cucumber",
      "score": null,
      "points": [
        [
          636.7857666015625,
          270.8197021484375
        ],
        [
          649.4483032226562,
          273.9483947753906
        ],
        [
          662.666748046875,
          284.7139892578125
        ],
        [
          673.7741088867188,
          298.14068603515625
        ],
        [
          688.952880859375,
          327.499267578125
        ],
        [
          707.8402709960938,
          368.63946533203125
        ],
        [
          729.1782836914062,
          408.44610595703125
        ],
        [
          748.35791015625,
          445.26849365234375
        ],
        [
          762.2266845703125,
          474.96185302734375
        ],
        [
          780.3364868164062,
          521.2510375976562
        ],
        [
          789.7425537109375,
          547.1346435546875
        ],
        [
          795.1476440429688,
          565.554443359375
        ],
        [
          795.5810546875,
          578.1729736328125
        ],
        [
          793.3944091796875,
          591.4610595703125
        ],
        [
          773.0881958007812,
          596.6504516601562
        ],
        [
          762.174072265625,
          586.7103881835938
        ],
        [
          748.8849487304688,
          567.4765625
        ],
        [
          731.4772338867188,
          526.6654663085938
        ],
        [
          703.1082763671875,
          470.268798828125
        ],
        [
          681.2849731445312,
          431.2933349609375
        ],
        [
          658.3211059570312,
          393.3164978027344
        ],
        [
          631.818359375,
          344.221923828125
        ],
        [
          614.9666137695312,
          311.0477600097656
        ],
        [
          611.9365234375,
          301.9215393066406
        ],
        [
          615.5794067382812,
          286.13970947265625
        ],
        [
          619.2693481445312,
          276.00335693359375
        ]
      ],
      "group_id": null,
      "description": "",
      "difficult": false,
      "shape_type": "polygon",
      "flags": {},
      "attributes": {},
      "kie_linking": []
    }
  ],
  "imagePath": "10_20210104_1894264_aug2.JPG",
  "imageData": null,
  "imageHeight": 720,
  "imageWidth": 1280
}